ansys/scade/apitools/__init__.py
ansys/scade/apitools/auto_scade_env.py
ansys/scade/apitools/create/__init__.py
ansys/scade/apitools/create/data_def.py
ansys/scade/apitools/create/declaration.py
ansys/scade/apitools/create/expression.py
ansys/scade/apitools/create/project.py
ansys/scade/apitools/create/scade.py
ansys/scade/apitools/create/type.py
ansys/scade/apitools/expr/__init__.py
ansys/scade/apitools/expr/access.py
ansys/scade/apitools/expr/predef.py
ansys/scade/apitools/info/__init__.py
ansys/scade/apitools/info/install.py
ansys/scade/apitools/info/runtime.py
ansys/scade/apitools/prop/__init__.py
ansys/scade/apitools/prop/pragma.py
ansys/scade/apitools/query/__init__.py
ansys/scade/apitools/query/type.py
ansys_scade_apitools-0.6.2.dist-info/licenses/LICENSE
ansys_scade_apitools-0.6.2.dist-info/WHEEL
ansys_scade_apitools-0.6.2.dist-info/METADATA
ansys_scade_apitools-0.6.2.dist-info/RECORD
