Metadata-Version: 2.4
Name: ansys-scade-apitools
Version: 0.6.2
Summary: An extension library for SCADE Python APIs.
Keywords: Scade,Api,Tools
Author-email: "Ansys, Inc." <pyansys.core@ansys.com>
Maintainer-email: "Ansys, Inc." <pyansys.core@ansys.com>
Requires-Python: >=3.7,!=3.8.*,!=3.9.*,!=3.11.*
Classifier: Development Status :: 4 - Beta
Classifier: Programming Language :: Python :: 3
Classifier: License :: OSI Approved :: MIT License
Classifier: Operating System :: Microsoft :: Windows
License-File: LICENSE
Requires-Dist: importlib-metadata >= 1.0; python_version < '3.8'
Requires-Dist: importlib-metadata >= 4.0; python_version >= '3.8'
Requires-Dist: build==1.2.2.post1 ; extra == "build"
Requires-Dist: twine==6.1.0 ; extra == "build"
Requires-Dist: ansys-sphinx-theme[autoapi]==1.3.2 ; extra == "doc"
Requires-Dist: autodoc_pydantic==2.2.0 ; extra == "doc"
Requires-Dist: jupyter_sphinx==0.5.3 ; extra == "doc"
Requires-Dist: nbsphinx==0.9.7 ; extra == "doc"
Requires-Dist: numpydoc==1.9.0 ; extra == "doc"
Requires-Dist: sphinx==8.1.3 ; extra == "doc"
Requires-Dist: sphinx-autoapi<=3.6.0 ; extra == "doc"
Requires-Dist: sphinx-autodoc-typehints==3.0.1 ; extra == "doc"
Requires-Dist: sphinxcontrib-globalsubs==0.1.2 ; extra == "doc"
Requires-Dist: sphinxcontrib-httpdomain==1.8.1 ; extra == "doc"
Requires-Dist: sphinx-copybutton==0.5.2 ; extra == "doc"
Requires-Dist: sphinx-jinja==2.0.2 ; extra == "doc"
Requires-Dist: sphinxnotes-strike==1.2.1 ; extra == "doc"
Requires-Dist: pytest==7.4.0 ; extra == "tests" and ( python_version < '3.8')
Requires-Dist: pytest-cov==4.1.0 ; extra == "tests" and ( python_version < '3.8')
Requires-Dist: pytest==8.4.1 ; extra == "tests" and ( python_version >= '3.8')
Requires-Dist: pytest-cov==6.2.1 ; extra == "tests" and ( python_version >= '3.8')
Project-URL: Discussions, https://github.com/ansys/scade-apitools/discussions
Project-URL: Documentation, https://apitools.scade.docs.pyansys.com
Project-URL: Homepage, https://www.ansys.com/products/embedded-software/ansys-scade-suite
Project-URL: Issues, https://github.com/ansys/scade-apitools/issues
Project-URL: Releases, https://github.com/ansys/scade-apitools/releases
Project-URL: Source, https://github.com/ansys/scade-apitools
Provides-Extra: build
Provides-Extra: doc
Provides-Extra: tests
